README.txt
bootstrap.py
buildout.cfg
setup.py
Products/__init__.py
Products.ZSyncer.egg-info/PKG-INFO
Products.ZSyncer.egg-info/SOURCES.txt
Products.ZSyncer.egg-info/dependency_links.txt
Products.ZSyncer.egg-info/not-zip-safe
Products.ZSyncer.egg-info/requires.txt
Products.ZSyncer.egg-info/top_level.txt
Products/ZSyncer/Config.py
Products/ZSyncer/ConfigUtils.py
Products/ZSyncer/ConnectionMgr.py
Products/ZSyncer/ZSyncer.py
Products/ZSyncer/ZSyncerTool.py
Products/ZSyncer/__init__.py
Products/ZSyncer/utils.py
Products/ZSyncer/zsyncer_icon.gif
Products/ZSyncer/Extensions/Install.py
Products/ZSyncer/dtml/Add.dtml
Products/ZSyncer/dtml/Approval.dtml
Products/ZSyncer/dtml/Edit.dtml
Products/ZSyncer/dtml/Folder.dtml
Products/ZSyncer/dtml/Sync.dtml
Products/ZSyncer/skins/zsyncer_skins/get_zsyncer_status_for_objects.py
Products/ZSyncer/skins/zsyncer_skins/zsyncer_delete.py
Products/ZSyncer/skins/zsyncer_skins/zsyncer_diff.zpt
Products/ZSyncer/skins/zsyncer_skins/zsyncer_folderview.zpt
Products/ZSyncer/skins/zsyncer_skins/zsyncer_objectview.zpt
Products/ZSyncer/skins/zsyncer_skins/zsyncer_result_template.zpt
Products/ZSyncer/skins/zsyncer_skins/zsyncer_sync.py
Products/ZSyncer/tests/__init__.py
Products/ZSyncer/tests/test_ConnectionMgr.py
Products/ZSyncer/tests/test_ZSyncer.py
Products/ZSyncer/tests/test_ZSyncerTool.py
Products/ZSyncer/www/Diff.zpt
Products/ZSyncer/www/SyncFolder.zpt
Products/ZSyncer/www/backup.gif
Products/ZSyncer/www/closed_folder.png
Products/ZSyncer/www/open_folder.png
Products/ZSyncer/www/transmission.gif
Products/ZSyncer/www/zsyncer_extra.gif
Products/ZSyncer/www/zsyncer_missing.gif
Products/ZSyncer/www/zsyncer_ok.gif
Products/ZSyncer/www/zsyncer_outdated.gif
docs/Makefile
docs/changes.txt
docs/conf.py
docs/credits.txt
docs/description.txt
docs/development.txt
docs/index.txt
docs/installation.txt
docs/license.txt
docs/make.bat
docs/todo.txt
docs/use.txt