Metadata-Version: 1.0
Name: Products.ZSyncer
Version: 1.0.1dev-r4448
Summary: ZSyncer is a project that allows live zope objects to be synchronized from one Zope to another without doing the tedious export / transfer / import dance
Home-page: http://pypi.python.org/pypi/Products.ZSyncer
Author: Paul M. Winkler, Chris Withers
Author-email: chris@simplistix.co.uk
License: UNKNOWN
Platform: UNKNOWN
Classifier: Development Status :: 5 - Production/Stable
Classifier: Intended Audience :: Developers
